mcpm/__init__.py
mcpm/__main__.py
mcpm/api.py
mcpm/cli.py
mcpm/common.py
mcpm/config.py
mcpm/geyser.py
mcpm/hangar.py
mcpm/modrinth.py
mcpm/paper.py
mcpm/provision.py
minecraft_package_manager-0.0.1.dist-info/METADATA
minecraft_package_manager-0.0.1.dist-info/WHEEL
minecraft_package_manager-0.0.1.dist-info/entry_points.txt
minecraft_package_manager-0.0.1.dist-info/licenses/LICENSE
minecraft_package_manager-0.0.1.dist-info/RECORD
