Metadata-Version: 2.4
Name: minecraft-package-manager
Version: 0.0.1
Summary: A tool for managing minecraft servers
Project-URL: Repository, https://github.com/woodrowbarlow/mcpm/
Author: Woodrow Barlow
License:                     GNU GENERAL PUBLIC LICENSE
License-File: LICENSE
Requires-Python: >=3.8
Requires-Dist: tomlkit>=0.13.3
